lgbt/__init__.py
lgbt/bars.py
lgbt/basicobjects.py
lgbt/consts.py
lgbt/core.py
lgbt/histogram.py
lgbt-2.3.4.dist-info/licenses/LICENSE
tests/__init__.py
tests/gui_test.py
tests/test_bars.py
tests/test_basicobjects.py
tests/test_core.py
tests/test_histogram.py
lgbt-2.3.4.dist-info/METADATA
lgbt-2.3.4.dist-info/WHEEL
lgbt-2.3.4.dist-info/top_level.txt
lgbt-2.3.4.dist-info/RECORD
