Metadata-Version: 2.4
Name: lgbt
Version: 2.3.4
Summary: Loading Graphical Bar Tracker
Author-email: Johan Sundstain <johansundstainx@gmail.com>
License-Expression: MIT
Project-URL: repository, https://github.com/JohanSundstain/Loading-Graphical-Bar-Tracker
Keywords: tracking,graphics,performance
Classifier: Programming Language :: Python :: 3
Classifier: Operating System :: OS Independent
Requires-Python: >=3.6
License-File: LICENSE
Requires-Dist: psutil
Requires-Dist: GPUtil
Requires-Dist: numpy
Requires-Dist: py-cpuinfo
Dynamic: license-file
